vidpack/__init__.py
vidpack/cli.py
vidpack/constants.py
vidpack/core.py
vidpack/helpers.py
vidpack/models.py
vidpack/utils.py
vidpack-0.3.3.dist-info/LICENSE
vidpack-0.3.3.dist-info/METADATA
vidpack-0.3.3.dist-info/WHEEL
vidpack-0.3.3.dist-info/entry_points.txt
vidpack-0.3.3.dist-info/RECORD
