Metadata-Version: 2.3
Name: vidpack
Version: 0.3.3
Summary: A Python script for efficiently compressing videos without sacrificing quality
License: MIT
Keywords: video,compression,ffmpeg,python
Author: ivansaul
Requires-Python: >=3.10,<4.0
Classifier: Development Status :: 3 - Alpha
Classifier: License :: OSI Approved :: MIT License
Classifier: Operating System :: OS Independent
Classifier: Programming Language :: Python :: 3
Classifier: Programming Language :: Python :: 3.10
Classifier: Programming Language :: Python :: 3.11
Classifier: Programming Language :: Python :: 3.12
Classifier: Programming Language :: Python :: 3.13
Classifier: Topic :: Multimedia :: Sound/Audio
Classifier: Topic :: Multimedia :: Video
Classifier: Topic :: Utilities
Requires-Dist: ffmpeg-progress-yield (>=0.9.1,<0.10.0)
Requires-Dist: python-ffmpeg (>=2.0.12,<3.0.0)
Requires-Dist: typer (>=0.12.5,<0.13.0)
Project-URL: Homepage, https://github.com/ivansaul/CLI-Video-Compressor
Project-URL: Repository, https://github.com/ivansaul/CLI-Video-Compressor
